Workbook

Sheet Name
D1: RELIANCE MF RETIREMENT CALCULATOR
D4: Welcome to Retirement Calculator
D6: Use the Retirement Calculator to find out the future value of your current expenses, calculate the retirement corpus you need to accumulate and how much you need to save to ensure you enjoy your golden post-retirement days.
D8: Enter Your Name:

Sheet Future Value
D2: RETIREMENT CALCULATOR
D6: Lets you know the Future Value of your current expenses | T6: 0.01
T7: =+T6+1% -> 0.02
T8: =+T7+1% -> 0.03
T9: =+T8+1% -> 0.04
T10: =+T9+1% -> 0.05
T11: =+T10+1% -> 0.06
D12: My Present Age | E12: Years | T12: =+T11+1% -> 0.07
T13: =+T12+1% -> 0.08
T14: =+T13+1% -> 0.09
D15: I am planning to retire at | E15: Years | G15: No. of years to retire: | H15: =+IF(F15-F12<0,"present age should be less than retirement age",(F15-F12)) -> 0 | T15: =+T14+1% -> 0.1
D18: Inflation rate
D21: Current Monthly Expenses: | E21: INR
D24: Future value of your current monthly expense: INR | G24: =IFERROR(D34,0) -> 0 | H24: =G24/10^5 -> 0 | I24: Lacs
D26: Notice how your future expenses are substantially higher, due to the effect of inflation. You have to save prudently to beat inflation and accumulate a sufficient retirement corpus to ensure that your future cost of living is comfortably met.
D31: Calculation Methodology: The above calculation is based on monthly compounding of the inflation rate you have assumed. For example, if you have assumed 6% inflation rate, 0.5% (6% divided by 12) monthly compounded rate is used for the time period between your present age and retirement.
D34: =IF(FV(F18/12,H15*12,0,-50000,0)=0," ",FV(F18/12,H15*12,0,-F21,0)) -> 0

Sheet Retirement Corpus
D2: RETIREMENT CALCULATOR | T2: 0.01
T3: =+T2+1% -> 0.02
T4: =+T3+1% -> 0.03
T5: =+T4+1% -> 0.04
T6: =+T5+1% -> 0.05
D7: Lets you calculate the retirement corpus for given post-retirement expenses. The expenses may be same as the previous step, or you may like to enter a different amount as per your choice | T7: =+T6+1% -> 0.06
T8: =+T7+1% -> 0.07
T9: =+T8+1% -> 0.08
T10: =+T9+1% -> 0.09
T11: =+T10+1% -> 0.1
T12: =+T11+1% -> 0.11
D13: Annuity per month | E13: INR | F13: =ROUND('Future Value'!G24,0) -> 0 | T13: =+T12+1% -> 0.12
T14: =+T13+1% -> 0.13
T15: =+T14+1% -> 0.14
D16: Life Expectancy (number of years post retirement) | E16: Years | T16: =+T15+1% -> 0.15
T17: =+T16+1% -> 0.16
T18: =+T17+1% -> 0.17
D19: Assumed Rate of Returns Post-Retirement | T19: =+T18+1% -> 0.18
T20: =+T19+1% -> 0.19
T21: =+T20+1% -> 0.2
D22: Your Retirement Corpus is: INR | F22: =IFERROR(-PV(F19/12,F16*12,F13,0,0),0) -> 0 | G22: =F22/10^7 -> 0 | H22: Crs. | T22: =+T21+1% -> 0.21
T23: =+T22+1% -> 0.22
D24: ="You have to make sure to have a minimum retirement corpus of Rs. "&ROUND(F22,0)&" to meet your post-retirement regular " -> You have to make sure to have a minimum retirement corpus of Rs. 0 to meet your post-retirement regular | T24: =+T23+1% -> 0.23
D25: expenses based on your assumptions. You may also like to consider building a higher retirement corpus to take care of | T25: =+T24+1% -> 0.24
D26: emergency expenses | T26: =+T25+1% -> 0.25
D32: Calculation Methodology: The above calculation is based on the assumption that monthly withdrawal is made on the retirement corpus at monthly compounding of the annual rate of return you have entered over the period of your life expectancy. For example, if you have entered 10% as the rate of return and life expectancy as 30 years, the calculator uses 0.83% (10% divided by 12) for 360 months (30 years multiplied by 12) to calculate the retirement corpus required for the monthly withdrawal amount. Please note that your retirement corpus will be completely used up, and will become nil at the end of life-expectancy.

Sheet Invest Per Month
D2: RETIREMENT CALCULATOR | S2: 0.01
S3: =+S2+1% -> 0.02
S4: =+S3+1% -> 0.03
S5: =+S4+1% -> 0.04
S6: =+S5+1% -> 0.05
D7: Lets you calculate the retirement corpus for given post-retirement expenses. The expenses may be same as the previous step, or you may like to enter a different amount as per your choice | S7: =+S6+1% -> 0.06
S8: =+S7+1% -> 0.07
S9: =+S8+1% -> 0.08
S10: =+S9+1% -> 0.09
S11: =+S10+1% -> 0.1
S12: =+S11+1% -> 0.11
D13: Your Retirement Corpus is | E13: INR | F13: =ROUND('Retirement Corpus'!F22:F22,0) -> 0 | S13: =+S12+1% -> 0.12
S14: =+S13+1% -> 0.13
S15: =+S14+1% -> 0.14
D16: Number of years left for retirement | E16: Years | F16: ='Future Value'!H15 -> 0 | S16: =+S15+1% -> 0.15
S17: =+S16+1% -> 0.16
S18: =+S17+1% -> 0.17
D19: How much would you invest right now as a lumpsum towards your retirement goal | E19: INR | S19: =+S18+1% -> 0.18
S20: =+S19+1% -> 0.19
S21: =+S20+1% -> 0.2
D22: Assumed Rate of Returns During Accumulation | S22: =+S21+1% -> 0.21
S23: =+S22+1% -> 0.22
S24: =+S23+1% -> 0.23
D25: How much you need to invest every month is INR: | F25: =IF(IFERROR(-PMT(F22/12,F16*12,-F19,F13,0),"0")>0,IFERROR(-PMT(F22/12,F16*12,-F19,F13,0),"0"),0) -> 0 | G25: =F25/10^3 -> 0 | H25: thousand | S25: =+S24+1% -> 0.24
S26: =+S25+1% -> 0.25
D27: ="You have to invest a minimum of Rs."&ROUND(F19,0)&" as lump sum and Rs."&ROUND(F25,0)&" monthy towards building your retirement corpus." -> You have to invest a minimum of Rs.0 as lump sum and Rs.0 monthy towards building your retirement corpus.
D28: ="You may also like to consider investing a higher amount and thereby, accumulate a higher retirement corpus to take care of emergency expenses." -> You may also like to consider investing a higher amount and thereby, accumulate a higher retirement corpus to take care of emergency expenses.
D33: Calculation Methodology: The above calculation is based on monthly compounding of the rate of return you have entered, over the number of years of your retirement for the required retirement corpus. For example, if you have entered 15% rate of return for 30 years, the calculator uses 1.25% (15% divided by 12) for 360 months (30 years multiplied by 12) to calculate the amount you need to save per month to accumulate your desired retirement corpus

Sheet Summary
F2: RETIREMENT CALCULATOR
G3: ="Dear "&Name!E8&"," -> Dear ,
G4: ="Based on your inputs and assumptions, you have "&ROUND('Invest Per Month'!F16,0)&" years to retire. You need to invest Rs."&ROUND('Invest Per Month'!F19,0) -> Based on your inputs and assumptions, you have 0 years to retire. You need to invest Rs.0
G5: ="as lump sum and "&ROUND('Invest Per Month'!F25,0)&" per month to accumulate a retirement corpus of Rs. "&ROUND('Retirement Corpus'!F22,0)&" which" -> as lump sum and 0 per month to accumulate a retirement corpus of Rs. 0 which
G6: ="could provide you a cash flow of Rs."&ROUND('Retirement Corpus'!F13,0)&" per month" -> could provide you a cash flow of Rs.0 per month
G8: ="Based on your current lumpsum investment of Rs."&ROUND('Invest Per Month'!F19,0) -> Based on your current lumpsum investment of Rs.0
G9: ="your possible retirement corpus could be Rs. "&ROUND(I21,0) -> your possible retirement corpus could be Rs. 0
G12: ="Present Age:"&" "&ROUND('Future Value'!F12,0)&" years" -> Present Age: 0 years
G14: ="Age of Retirement:"&" "&ROUND('Future Value'!F15,0)&" years" -> Age of Retirement: 0 years
G16: ="Monthly Withdrawal Post Retirement: Rs." -> Monthly Withdrawal Post Retirement: Rs. | J16: =ROUND('Retirement Corpus'!F13,0) -> 0 | N16: =IF(J16/10^5=0,0.00001,J16/10^5) -> 1e-05 | O16: lacs
G18: ="Retirement Corpus Required:"&" Rs." -> Retirement Corpus Required: Rs. | I18: =ROUND('Retirement Corpus'!F22,0) -> 0 | N18: =IF(I18/10^7=0,0.00001,I18/10^7) -> 1e-05 | O18: Crs.
G21: Possible Retirement Corpus: Rs. | I21: =IFERROR(IF(FV('Invest Per Month'!F22/12,'Invest Per Month'!F16*12,,-'Invest Per Month'!F19,0)>I18,FV('Invest Per Month'!F22/12,'Invest Per Month'!F16*12,,-'Invest Per Month'!F19,0),I18),0) -> 0 | N21: =IF(I21/10^7=0,0.00001,I21/10^7) -> 1e-05 | O21: Crs.
G24: ="Lump sum amount to be invested today: Rs." -> Lump sum amount to be invested today: Rs. | K24: =IF(ROUND('Invest Per Month'!F19,0)=0,0.1,ROUND('Invest Per Month'!F19,0)) -> 0.1 | N24: =K24/10^5 -> 1e-06 | O24: lacs
G26: ="Amount to invest per month:"&" Rs." -> Amount to invest per month: Rs. | I26: =IF(ROUND('Invest Per Month'!F25,0)=0,0.001,ROUND('Invest Per Month'!F25,0)) -> 0.001 | N26: =I26/10^3 -> 1e-06 | O26: thousand
G30: Disclaimer: This calculator is provided to enable you to plan your retirement and aid an estimate for the retirement benefit. It is designed only for information / education purpose. The results presented by this calculator are hypothetical and basis the information / inputs provided by you and guides you to plan your retirement and importance of savings for your retirement benefits. . Kindly do not consider this as an investment advice or direct or indirect solicitation for the scheme or the performance. While utmost care has been exercised in preparing this calculator, Reliance Capital Asset Management Limited / Reliance Trustee Co. Ltd/ Sponsor or their respective directors, employees, affiliates or representatives do not warrant the completeness or guarantee the accuracy of the information and will not be responsible for any liabilities, losses, damages arising out of the use or in respect of anything done in reliance of the calculator. The calculations provided through this calculator shall not directly or indirectly be construed as solicitation of scheme the performance of the scheme. Request you consult your financial advisor before making any type of investment.
